[
  { "_id": "1", "student": "130", "assignment": "A201", "grade": "99" },
  { "_id": "2", "student": "131", "assignment": "A201", "grade": "87" },
  { "_id": "3", "student": "132", "assignment": "A201", "grade": "88" },
  { "_id": "4", "student": "133", "assignment": "A201", "grade": "89" },
  { "_id": "5", "student": "134", "assignment": "A201", "grade": "100" },
  { "_id": "6", "student": "135", "assignment": "A201", "grade": "96" },
  { "_id": "7", "student": "136", "assignment": "A201", "grade": "87" },
  { "_id": "8", "student": "137", "assignment": "A201", "grade": "98" },
  { "_id": "9", "student": "138", "assignment": "A201", "grade": "86" },
  { "_id": "10", "student": "139", "assignment": "A201", "grade": "94" },
  { "_id": "11", "student": "130", "assignment": "A202", "grade": "97" },
  { "_id": "12", "student": "131", "assignment": "A202", "grade": "90" },
  { "_id": "13", "student": "132", "assignment": "A202", "grade": "86" },
  { "_id": "14", "student": "133", "assignment": "A202", "grade": "85" },
  { "_id": "15", "student": "134", "assignment": "A202", "grade": "97" },
  { "_id": "16", "student": "135", "assignment": "A202", "grade": "88" },
  { "_id": "17", "student": "136", "assignment": "A202", "grade": "86" },
  { "_id": "18", "student": "137", "assignment": "A202", "grade": "90" },
  { "_id": "19", "student": "138", "assignment": "A202", "grade": "97" },
  { "_id": "20", "student": "139", "assignment": "A202", "grade": "98" },
  { "_id": "21", "student": "130", "assignment": "A203", "grade": "87" },
  { "_id": "22", "student": "131", "assignment": "A203", "grade": "93" },
  { "_id": "23", "student": "132", "assignment": "A203", "grade": "86" },
  { "_id": "24", "student": "133", "assignment": "A203", "grade": "97" },
  { "_id": "25", "student": "134", "assignment": "A203", "grade": "99" },
  { "_id": "26", "student": "135", "assignment": "A203", "grade": "89" },
  { "_id": "27", "student": "136", "assignment": "A203", "grade": "99" },
  { "_id": "28", "student": "137", "assignment": "A203", "grade": "87" },
  { "_id": "29", "student": "138", "assignment": "A203", "grade": "100" },
  { "_id": "30", "student": "139", "assignment": "A203", "grade": "91" },
  { "_id": "31", "student": "130", "assignment": "A204", "grade": "86" },
  { "_id": "32", "student": "131", "assignment": "A204", "grade": "90" },
  { "_id": "33", "student": "132", "assignment": "A204", "grade": "94" },
  { "_id": "34", "student": "133", "assignment": "A204", "grade": "89" },
  { "_id": "35", "student": "134", "assignment": "A204", "grade": "97" },
  { "_id": "36", "student": "135", "assignment": "A204", "grade": "99" },
  { "_id": "37", "student": "136", "assignment": "A204", "grade": "98" },
  { "_id": "38", "student": "137", "assignment": "A204", "grade": "87" },
  { "_id": "39", "student": "138", "assignment": "A204", "grade": "90" },
  { "_id": "40", "student": "139", "assignment": "A204", "grade": "93" },
  { "_id": "41", "student": "130", "assignment": "A301", "grade": "86" },
  { "_id": "42", "student": "131", "assignment": "A301", "grade": "100" },
  { "_id": "43", "student": "132", "assignment": "A301", "grade": "85" },
  { "_id": "44", "student": "133", "assignment": "A301", "grade": "95" },
  { "_id": "45", "student": "134", "assignment": "A301", "grade": "94" },
  { "_id": "46", "student": "135", "assignment": "A301", "grade": "91" },
  { "_id": "47", "student": "136", "assignment": "A301", "grade": "89" },
  { "_id": "48", "student": "137", "assignment": "A301", "grade": "99" },
  { "_id": "49", "student": "138", "assignment": "A301", "grade": "89" },
  { "_id": "50", "student": "139", "assignment": "A301", "grade": "94" },
  { "_id": "51", "student": "130", "assignment": "A302", "grade": "99" },
  { "_id": "52", "student": "131", "assignment": "A302", "grade": "87" },
  { "_id": "53", "student": "132", "assignment": "A302", "grade": "94" },
  { "_id": "54", "student": "133", "assignment": "A302", "grade": "99" },
  { "_id": "55", "student": "134", "assignment": "A302", "grade": "86" },
  { "_id": "56", "student": "135", "assignment": "A302", "grade": "94" },
  { "_id": "57", "student": "136", "assignment": "A302", "grade": "91" },
  { "_id": "58", "student": "137", "assignment": "A302", "grade": "100" },
  { "_id": "59", "student": "138", "assignment": "A302", "grade": "98" },
  { "_id": "60", "student": "139", "assignment": "A302", "grade": "89" },
  { "_id": "61", "student": "130", "assignment": "A303", "grade": "90" },
  { "_id": "62", "student": "131", "assignment": "A303", "grade": "100" },
  { "_id": "63", "student": "132", "assignment": "A303", "grade": "94" },
  { "_id": "64", "student": "133", "assignment": "A303", "grade": "98" },
  { "_id": "65", "student": "134", "assignment": "A303", "grade": "94" },
  { "_id": "66", "student": "135", "assignment": "A303", "grade": "85" },
  { "_id": "67", "student": "136", "assignment": "A303", "grade": "95" },
  { "_id": "68", "student": "137", "assignment": "A303", "grade": "92" },
  { "_id": "69", "student": "138", "assignment": "A303", "grade": "92" },
  { "_id": "70", "student": "139", "assignment": "A303", "grade": "93" },
  { "_id": "71", "student": "130", "assignment": "A304", "grade": "100" },
  { "_id": "72", "student": "131", "assignment": "A304", "grade": "90" },
  { "_id": "73", "student": "132", "assignment": "A304", "grade": "87" },
  { "_id": "74", "student": "133", "assignment": "A304", "grade": "90" },
  { "_id": "75", "student": "134", "assignment": "A304", "grade": "89" },
  { "_id": "76", "student": "135", "assignment": "A304", "grade": "96" },
  { "_id": "77", "student": "136", "assignment": "A304", "grade": "99" },
  { "_id": "78", "student": "137", "assignment": "A304", "grade": "96" },
  { "_id": "79", "student": "138", "assignment": "A304", "grade": "87" },
  { "_id": "80", "student": "139", "assignment": "A304", "grade": "99" },
  { "_id": "81", "student": "130", "assignment": "A401", "grade": "87" },
  { "_id": "82", "student": "131", "assignment": "A401", "grade": "86" },
  { "_id": "83", "student": "132", "assignment": "A401", "grade": "92" },
  { "_id": "84", "student": "133", "assignment": "A401", "grade": "87" },
  { "_id": "85", "student": "134", "assignment": "A401", "grade": "88" },
  { "_id": "86", "student": "135", "assignment": "A401", "grade": "98" },
  { "_id": "87", "student": "136", "assignment": "A401", "grade": "97" },
  { "_id": "88", "student": "137", "assignment": "A401", "grade": "89" },
  { "_id": "89", "student": "138", "assignment": "A401", "grade": "95" },
  { "_id": "90", "student": "139", "assignment": "A401", "grade": "98" },
  { "_id": "91", "student": "130", "assignment": "A402", "grade": "89" },
  { "_id": "92", "student": "131", "assignment": "A402", "grade": "87" },
  { "_id": "93", "student": "132", "assignment": "A402", "grade": "91" },
  { "_id": "94", "student": "133", "assignment": "A402", "grade": "96" },
  { "_id": "95", "student": "134", "assignment": "A402", "grade": "90" },
  { "_id": "96", "student": "135", "assignment": "A402", "grade": "89" },
  { "_id": "97", "student": "136", "assignment": "A402", "grade": "98" },
  { "_id": "98", "student": "137", "assignment": "A402", "grade": "90" },
  { "_id": "99", "student": "138", "assignment": "A402", "grade": "86" },
  { "_id": "100", "student": "139", "assignment": "A402", "grade": "89" },
  { "_id": "101", "student": "130", "assignment": "A403", "grade": "100" },
  { "_id": "102", "student": "131", "assignment": "A403", "grade": "86" },
  { "_id": "103", "student": "132", "assignment": "A403", "grade": "93" },
  { "_id": "104", "student": "133", "assignment": "A403", "grade": "88" },
  { "_id": "105", "student": "134", "assignment": "A403", "grade": "100" },
  { "_id": "106", "student": "135", "assignment": "A403", "grade": "88" },
  { "_id": "107", "student": "136", "assignment": "A403", "grade": "92" },
  { "_id": "108", "student": "137", "assignment": "A403", "grade": "87" },
  { "_id": "109", "student": "138", "assignment": "A403", "grade": "88" },
  { "_id": "110", "student": "139", "assignment": "A403", "grade": "98" },
  { "_id": "111", "student": "130", "assignment": "A404", "grade": "100" },
  { "_id": "112", "student": "131", "assignment": "A404", "grade": "88" },
  { "_id": "113", "student": "132", "assignment": "A404", "grade": "88" },
  { "_id": "114", "student": "133", "assignment": "A404", "grade": "100" },
  { "_id": "115", "student": "134", "assignment": "A404", "grade": "100" },
  { "_id": "116", "student": "135", "assignment": "A404", "grade": "93" },
  { "_id": "117", "student": "136", "assignment": "A404", "grade": "87" },
  { "_id": "118", "student": "137", "assignment": "A404", "grade": "100" },
  { "_id": "119", "student": "138", "assignment": "A404", "grade": "88" },
  { "_id": "120", "student": "139", "assignment": "A404", "grade": "98" },
  { "_id": "121", "student": "130", "assignment": "A501", "grade": "93" },
  { "_id": "122", "student": "131", "assignment": "A501", "grade": "89" },
  { "_id": "123", "student": "132", "assignment": "A501", "grade": "94" },
  { "_id": "124", "student": "133", "assignment": "A501", "grade": "91" },
  { "_id": "125", "student": "134", "assignment": "A501", "grade": "85" },
  { "_id": "126", "student": "135", "assignment": "A501", "grade": "99" },
  { "_id": "127", "student": "136", "assignment": "A501", "grade": "98" },
  { "_id": "128", "student": "137", "assignment": "A501", "grade": "85" },
  { "_id": "129", "student": "138", "assignment": "A501", "grade": "99" },
  { "_id": "130", "student": "139", "assignment": "A501", "grade": "94" },
  { "_id": "131", "student": "130", "assignment": "A502", "grade": "88" },
  { "_id": "132", "student": "131", "assignment": "A502", "grade": "98" },
  { "_id": "133", "student": "132", "assignment": "A502", "grade": "97" },
  { "_id": "134", "student": "133", "assignment": "A502", "grade": "85" },
  { "_id": "135", "student": "134", "assignment": "A502", "grade": "96" },
  { "_id": "136", "student": "135", "assignment": "A502", "grade": "90" },
  { "_id": "137", "student": "136", "assignment": "A502", "grade": "99" },
  { "_id": "138", "student": "137", "assignment": "A502", "grade": "97" },
  { "_id": "139", "student": "138", "assignment": "A502", "grade": "86" },
  { "_id": "140", "student": "139", "assignment": "A502", "grade": "95" },
  { "_id": "141", "student": "130", "assignment": "A503", "grade": "89" },
  { "_id": "142", "student": "131", "assignment": "A503", "grade": "91" },
  { "_id": "143", "student": "132", "assignment": "A503", "grade": "94" },
  { "_id": "144", "student": "133", "assignment": "A503", "grade": "91" },
  { "_id": "145", "student": "134", "assignment": "A503", "grade": "93" },
  { "_id": "146", "student": "135", "assignment": "A503", "grade": "95" },
  { "_id": "147", "student": "136", "assignment": "A503", "grade": "90" },
  { "_id": "148", "student": "137", "assignment": "A503", "grade": "86" },
  { "_id": "149", "student": "138", "assignment": "A503", "grade": "87" },
  { "_id": "150", "student": "139", "assignment": "A503", "grade": "91" },
  { "_id": "151", "student": "130", "assignment": "A504", "grade": "96" },
  { "_id": "152", "student": "131", "assignment": "A504", "grade": "100" },
  { "_id": "153", "student": "132", "assignment": "A504", "grade": "93" },
  { "_id": "154", "student": "133", "assignment": "A504", "grade": "89" },
  { "_id": "155", "student": "134", "assignment": "A504", "grade": "97" },
  { "_id": "156", "student": "135", "assignment": "A504", "grade": "88" },
  { "_id": "157", "student": "136", "assignment": "A504", "grade": "91" },
  { "_id": "158", "student": "137", "assignment": "A504", "grade": "89" },
  { "_id": "159", "student": "138", "assignment": "A504", "grade": "90" },
  { "_id": "160", "student": "139", "assignment": "A504", "grade": "99" }
]
